{"\/":1443,"\/featured":3,"\/about":29,"\/blog\/2014-01-10-theme-elements":31,"\/blog\/2014-01-08-a-quotation":3,"\/blog\/2013-12-30-readability-feature-post":4,"\/categories":2,"\/contacto":77,"\/blog\/relog-canvas":31,"\/blog\/first-commit":24,"\/login":3,"\/user_register":2,"\/thankyou":3,"\/blog\/sample-link-post":1,"\/blog\/2014-11-30-why-grav":1,"\/blog\/primera-entrada":12,"\/blog\/quiz-html":9,"\/blog\/flat-file-cms":9,"\/blog\/quiz-css":1,"\/blog\/tag-manager":1,"\/blog\/carpetas-de-grav-cms":12}